{
  "date": "2026-04-15",
  "timestamp": "2026-04-15T16:05:05.797552",
  "usdjpy": 158.95,
  "ranking": [
    {
      "bot": "Bot9_VolAsymmetry",
      "total_return": 0.0018,
      "mdd": -0.0082,
      "win_rate": 0.3667,
      "sharpe": 0.07,
      "n_trades": 86,
      "latest_equity": 1001829.0,
      "days": 90,
      "rank": 1,
      "score": 0.77,
      "profit_jpy": 1829.0,
      "daily_target": 10018.0
    },
    {
      "bot": "Bot6_RL_MA",
      "total_return": -0.0007,
      "mdd": -0.0099,
      "win_rate": 0.4222,
      "sharpe": 0.32,
      "n_trades": 71,
      "latest_equity": 999298.0,
      "days": 90,
      "rank": 2,
      "score": 0.793,
      "profit_jpy": -702.0,
      "daily_target": 9993.0
    },
    {
      "bot": "Bot11_SubspacePCA",
      "total_return": -0.0029,
      "mdd": -0.0043,
      "win_rate": 0.3444,
      "sharpe": 0.33,
      "n_trades": 78,
      "latest_equity": 997050.0,
      "days": 90,
      "rank": 3,
      "score": 0.6995,
      "profit_jpy": -2950.0,
      "daily_target": 9970.0
    },
    {
      "bot": "Bot1_ML_AbsChange",
      "total_return": -0.0033,
      "mdd": -0.0092,
      "win_rate": 0.5,
      "sharpe": -0.52,
      "n_trades": 74,
      "latest_equity": 996657.0,
      "days": 90,
      "rank": 4,
      "score": 0.8006,
      "profit_jpy": -3343.0,
      "daily_target": 9967.0
    },
    {
      "bot": "Bot7_AdaptiveMarket",
      "total_return": -0.0124,
      "mdd": -0.0055,
      "win_rate": 0.3222,
      "sharpe": -0.73,
      "n_trades": 68,
      "latest_equity": 987567.0,
      "days": 90,
      "rank": 5,
      "score": 0.576,
      "profit_jpy": -12433.0,
      "daily_target": 9876.0
    },
    {
      "bot": "Bot5_TrendMomentum",
      "total_return": -0.0137,
      "mdd": -0.0078,
      "win_rate": 0.3444,
      "sharpe": -2.1,
      "n_trades": 61,
      "latest_equity": 986292.0,
      "days": 90,
      "rank": 6,
      "score": 0.5605,
      "profit_jpy": -13708.0,
      "daily_target": 9863.0
    },
    {
      "bot": "Bot2_DL_Transformer",
      "total_return": -0.0394,
      "mdd": -0.0354,
      "win_rate": 0.2,
      "sharpe": -4.85,
      "n_trades": 54,
      "latest_equity": 960576.0,
      "days": 90,
      "rank": 7,
      "score": 0.2582,
      "profit_jpy": -39424.0,
      "daily_target": 9606.0
    },
    {
      "bot": "Bot8_NewsTech",
      "total_return": -0.0411,
      "mdd": -0.0367,
      "win_rate": 0.3222,
      "sharpe": -4.95,
      "n_trades": 48,
      "latest_equity": 958943.0,
      "days": 90,
      "rank": 8,
      "score": 0.3263,
      "profit_jpy": -41057.0,
      "daily_target": 9589.0
    },
    {
      "bot": "Bot3_FactorAI",
      "total_return": -0.0493,
      "mdd": -0.0466,
      "win_rate": 0.2667,
      "sharpe": -7.57,
      "n_trades": 69,
      "latest_equity": 950745.0,
      "days": 90,
      "rank": 9,
      "score": 0.1945,
      "profit_jpy": -49255.0,
      "daily_target": 9507.0
    }
  ]
}