[
  {
    "date": "2026-03-22",
    "generated_at": "2026-03-23 07:00",
    "total_jpy": 1000000,
    "daily_pnl": 0,
    "monthly_pnl": 0,
    "monthly_return": 0.0,
    "gap_to_target": 30.0,
    "trade_count": 0,
    "report": {
      "morning_greeting": "おはようございます。本日の報告です。",
      "daily_result": "昨日の損益は¥0でした。取引件数0件のため、ポジションなしの状態を維持しております。総資産¥1,000,000は現金として待機中です。",
      "market_summary": "<cite index=\"1-1,3-1\">昨日20日、金価格が2%下落し4570ドルまで下落、ドル円は157.73円から159.23円まで円安が進行</cite>。<cite index=\"2-2\">日経平均は急反発し+1500円の大幅上昇</cite>。<cite index=\"4-1\">米国株は調整入りし約1年で最長の週足下落</cite>となりました。",
      "monthly_progress": "月次進捗：損益¥0、リターン0.00%で目標月利30%（¥300,000利益必要）まで30%残り。月初から取引機会を見送り続けており、リスク管理重視の姿勢を継続中。",
      "today_strategy": "<cite index=\"5-3\">ドル円は158.00円のオプション（3/24-25日満期）が重要な引力として機能予想</cite>。<cite index=\"1-1\">中東情勢緊迫化と各国の利上げ観測</cite>を注視し、ボラティリティ拡大を慎重に見極めて参ります。",
      "alert": "中東情勢の緊迫化により市場ボラティリティが極めて高い状態です。有事のドル買いとインフレ懸念による利上げ観測が混在しており、急激な相場変動リスクに十分ご注意ください。"
    },
    "rate": 159.32
  },
  {
    "date": "2026-03-23",
    "generated_at": "2026-03-24 07:00",
    "total_jpy": 1000000,
    "daily_pnl": 0,
    "monthly_pnl": 0,
    "monthly_return": 0.0,
    "gap_to_target": 30.0,
    "trade_count": 0,
    "report": {
      "morning_greeting": "おはようございます。本日の報告です。",
      "daily_result": "昨日は取引なしで損益¥+0。現金残高¥1,000,000を維持。月次進捗は目標の¥300,000に対し未達状況が続いております。",
      "market_summary": "昨日の日経平均は大幅続落、終値51,515円（-1,857円、-3.48%）。中東情勢悪化による米株安とリスクオフが主因。ドル円は159円台で推移。",
      "monthly_progress": "月次損益¥+0、リターン+0.00%で目標月利30%（¥300,000）に対し大幅未達。3月残り8日間での挽回が必要な状況。",
      "today_strategy": "中東情勢による市場不安定化が継続。リスクオン回復のタイミングを見極め、慎重な押し目買いを検討。160円近辺での為替介入リスクにも注意。",
      "alert": "市場の変動が激しく、急反発の可能性も。リスク管理を最優先に、損切りラインの徹底を。"
    },
    "rate": 158.38
  },
  {
    "date": "2026-03-24",
    "generated_at": "2026-03-25 07:00",
    "total_jpy": 1000754,
    "daily_pnl": 0,
    "monthly_pnl": 1431,
    "monthly_return": 0.08,
    "gap_to_target": 29.92,
    "trade_count": 0,
    "report": {
      "morning_greeting": "おはようございます。本日の報告です。",
      "daily_result": "昨日は取引実績なしで損益は+0円。総資産は100万754円と堅調な水準を維持。現金残高が全額保持されている状況で、次の投資機会を探る体制です。",
      "market_summary": "昨日の日本株は<cite index=\"1-1,4-1\">大幅下落で値下がり率ランキング上位は31%超の下落</cite>。<cite index=\"6-2,16-2\">中東情勢不安からリスク回避が拡大し、ドル円は159円台前半から158円台まで下落</cite>しました。",
      "monthly_progress": "月次損益は+1,431円（+0.08%）と順調に推移。目標の月利30%（130万円）まで残り29.92%で、あと約29万9千円の収益が必要。現在の取引数は3件と控えめ。",
      "today_strategy": "<cite index=\"8-1\">本日は日経平均が前場で394円高と反発</cite>。中東情勢の一時的緩和を受けた反発相場を慎重に観察し、適切なエントリータイミングを見極めます。",
      "alert": "中東情勢は不安定で相場変動が大きい状況。投資タイミングは慎重に判断し、目標達成に向けたリスク管理を徹底してください。"
    },
    "rate": 158.64
  },
  {
    "date": "2026-03-25",
    "generated_at": "2026-03-26 07:00",
    "total_jpy": 1000000,
    "daily_pnl": 0,
    "monthly_pnl": 0,
    "monthly_return": 0.0,
    "gap_to_target": 30.0,
    "trade_count": 0,
    "report": {
      "morning_greeting": "おはようございます。本日の報告です。",
      "daily_result": "昨日3月24日は取引を見送り、損益±0円でした。総資産¥1,000,000（現金¥1,000,000）で変動なし。月次累計も±0円を維持。",
      "market_summary": "日経平均は反発し+736円（+1.43%）の52,252円で終了。米中東停戦期待から買い戻しが優勢。ドル円は158円台で推移、原油も一時反落したが不安定な状況継続。",
      "monthly_progress": "3月の月次リターンは+0.00%、目標30%（¥1,300,000）まで残り30.00%。<cite index=\"1-1,2-1\">市場は中東情勢緊迫による材料相場で値動きが激しく</cite>、慎重な姿勢を継続中。",
      "today_strategy": "中東情勢による不安定相場が継続中のため、引き続き様子見を基本とします。<cite index=\"1-3,2-2\">停戦交渉期待がある一方で警戒感も根強く</cite>、明確なトレンド転換まで静観予定。",
      "alert": "原油価格と円安進行が家計コストに影響する可能性あり。為替介入への警戒も継続。"
    },
    "rate": 159.38
  }
]